dgsmb/__init__.py
dgsmb/config.py
dgsmb/decorator.py
dgsmb-1.0.0a7.dist-info/licenses/LICENSE
dgsmb-1.0.0a7.dist-info/METADATA
dgsmb-1.0.0a7.dist-info/WHEEL
dgsmb-1.0.0a7.dist-info/top_level.txt
dgsmb-1.0.0a7.dist-info/RECORD
